azureChatGPT/__init__.py
azureChatGPT/__main__.py
azureChatGPT/azure.py
azureChatGPT/utils.py
azureChatGPT-0.0.5.dist-info/LICENSE
azureChatGPT-0.0.5.dist-info/METADATA
azureChatGPT-0.0.5.dist-info/WHEEL
azureChatGPT-0.0.5.dist-info/top_level.txt
azureChatGPT-0.0.5.dist-info/RECORD
